{
    "host":"http://localhost:3000",
    "path":{
        "initGame":"/game/players",
        "getGameForPlayers":"/game/players/{gameId}",
        "getGameForOthers":"/game/others/{gameId}",
        "putGameStep":"/game/players/{gameId}/step",
        "putAttackShield":"/game/players/{gameId}/attack/shield",
        "putAttackDirect":"/game/players/{gameId}/attack/dicrect",
        "postManaCharge":"/game/players/{gameId}/mana/charge",
        "postCreature":"/game/players/{gameId}/creature",
        "getStandByGame":"/game/standby",
        "deleteStandByGame":"/game/standby/{standbyId}",
        "signUp":"/auth/signup",
        "signUpVerify":"/auth/verify/{tempUserId}",
        "signin":"/auth/signin",
        "getUser":"/user",
        "getUsers":"/user/info",
        "initDefaultGame":"/deck/default",
        "getDefaultGame":"/deck/default",
        "mockGame":"/game/mock",
        "mockCard":"/card/mock"
    }
}
